Excalibur2/Excalibur2.py
Excalibur2/__init__.py
Excalibur2/__update__.py
Excalibur2-2.4.dist-info/LICENSE
Excalibur2-2.4.dist-info/METADATA
Excalibur2-2.4.dist-info/WHEEL
Excalibur2-2.4.dist-info/top_level.txt
Excalibur2-2.4.dist-info/RECORD
