Metadata-Version: 2.1
Name: Excalibur2
Version: 2.4
Summary: A simple tool for pwn learners
Author-email: lmarch2 <2524158037@qq.cm>
Project-URL: Homepage, https://lmarch2.top/
Classifier: Programming Language :: Python :: 3
Classifier: License :: OSI Approved :: MIT License
Classifier: Operating System :: OS Independent
Requires-Python: >=3.8
License-File: LICENSE
